pycomb/__init__.py
pycomb/combinators.py
pycomb/context.py
pycomb/decorators.py
pycomb/exceptions.py
pycomb/predicates.py
pycomb/test/__init__.py
pycomb/test/test_combinators.py
pycomb/test/test_decorators.py
pycomb/test/test_list.py
pycomb/test/test_predicates.py
pycomb/test/util.py
pycomb-0.1.6.dist-info/DESCRIPTION.rst
pycomb-0.1.6.dist-info/METADATA
pycomb-0.1.6.dist-info/RECORD
pycomb-0.1.6.dist-info/WHEEL
pycomb-0.1.6.dist-info/metadata.json
pycomb-0.1.6.dist-info/top_level.txt
