Metadata-Version: 2.0
Name: pycomb
Version: 0.1.6
Summary: Python combination
Home-page: https://github.com/fcracker79/pycomb
Author: fcracker79
Author-email: fcracker79@gmail.com
License: MIT
Keywords: type hinting validation combinator
Platform: UNKNOWN
Classifier: Development Status :: 4 - Beta
Classifier: Intended Audience :: Developers
Classifier: Topic :: Software Development
Classifier: License :: OSI Approved :: MIT License
Classifier: Programming Language :: Python :: 3.2
Classifier: Programming Language :: Python :: 3.3
Classifier: Programming Language :: Python :: 3.4
Classifier: Programming Language :: Python :: 3.5
Requires-Dist: coverage (==4.2)
